BDPotentiometer/__gpiozero_helpers.py
BDPotentiometer/__helpers.py
BDPotentiometer/__init__.py
BDPotentiometer/__logger.py
BDPotentiometer/digital_potentiometer.py
BDPotentiometer/digital_wiper.py
BDPotentiometer/potentiometer.py
BDPotentiometer/mcp4xxx/__init__.py
BDPotentiometer/mcp4xxx/mcp4xx1.py
BDPotentiometer/mcp4xxx/mcp4xx2.py
BDPotentiometer/mcp4xxx/mcp4xxx.py
BDPotentiometer-0.1.0.dist-info/LICENSE
BDPotentiometer-0.1.0.dist-info/METADATA
BDPotentiometer-0.1.0.dist-info/WHEEL
BDPotentiometer-0.1.0.dist-info/top_level.txt
BDPotentiometer-0.1.0.dist-info/RECORD
