Metadata-Version: 2.1
Name: BDPotentiometer
Version: 0.1.0
Summary: BD Digital Potentiometer
Author-email: Anton Bondarenko <bond.anton@gmail.com>
License: MIT License
Project-URL: Homepage, https://github.com/bond-anton/BDPotentiometer
Project-URL: Bug Tracker, https://github.com/bond-anton/BDPotentiometer/issues
Project-URL: Documentation, https://bdpotentiometer.readthedocs.io
Classifier: Programming Language :: Python :: 3
Classifier: License :: OSI Approved :: MIT License
Classifier: Operating System :: OS Independent
Requires-Python: >=3.9
License-File: LICENSE
Requires-Dist: gpiozero >=1.6.2
Provides-Extra: dev
Requires-Dist: gpiozero >=1.6.2 ; extra == 'dev'
Requires-Dist: numpy ; extra == 'dev'
Provides-Extra: lint
Requires-Dist: pylint ; extra == 'lint'
Provides-Extra: test
Requires-Dist: flake8 ; extra == 'test'
Requires-Dist: pytest ; extra == 'test'
Requires-Dist: numpy ; extra == 'test'
